magmaviz/__init__.py
magmaviz/boxplot.py
magmaviz/corrplot.py
magmaviz/histogram.py
magmaviz/magmaviz.py
magmaviz/scatterplot.py
magmaviz-0.4.3.dist-info/LICENSE
magmaviz-0.4.3.dist-info/WHEEL
magmaviz-0.4.3.dist-info/METADATA
magmaviz-0.4.3.dist-info/RECORD
