Metadata-Version: 2.1
Name: magmaviz
Version: 0.4.3
Summary: This package contains four different data visualization functions with the magma theme for EDA.
License: MIT
Author: Abdul Moid Mohammed, Mukund Iyer, Irene Yan, Rubén De la Garza Macías
Requires-Python: >=3.9,<4.0
Classifier: License :: OSI Approved :: MIT License
Classifier: Programming Language :: Python :: 3
Classifier: Programming Language :: Python :: 3.10
Classifier: Programming Language :: Python :: 3.9
Requires-Dist: altair (>=4.2.0,<5.0.0)
Requires-Dist: pandas (>=1.3.5,<2.0.0)
Requires-Dist: vega-datasets (>=0.9.0,<0.10.0)
